psycopg2_iam/__init__.py
psycopg2_iam-1.1.0.dist-info/LICENSE
psycopg2_iam-1.1.0.dist-info/WHEEL
psycopg2_iam-1.1.0.dist-info/METADATA
psycopg2_iam-1.1.0.dist-info/RECORD
