Metadata-Version: 2.1
Name: psycopg2-iam
Version: 1.1.0
Summary: Custom Connection Factory class (RDS, Redshift) with build-in IAM authentication and SSL bundle downloader support.
Home-page: https://github.com/epsyhealth/psycopg2-iam
License: MIT
Keywords: aws,rds,redshift
Author: Epsy Engineering
Author-email: engineering@epsyhealth.com
Requires-Python: >=3.8,<4.0
Classifier: Intended Audience :: Developers
Classifier: License :: OSI Approved :: MIT License
Classifier: Programming Language :: Python
Classifier: Programming Language :: Python :: 3
Classifier: Programming Language :: Python :: 3 :: Only
Classifier: Programming Language :: Python :: 3.8
Classifier: Programming Language :: Python :: 3.9
Classifier: Topic :: Database
Requires-Dist: boto3 (>=1.14,<2.0)
Requires-Dist: psycopg2-binary (>=2.8,<3.0)
Project-URL: Repository, https://github.com/epsyhealth/psycopg2-iam
